wac.py
finix_wac-0.31.dist-info/DESCRIPTION.rst
finix_wac-0.31.dist-info/METADATA
finix_wac-0.31.dist-info/RECORD
finix_wac-0.31.dist-info/WHEEL
finix_wac-0.31.dist-info/metadata.json
finix_wac-0.31.dist-info/top_level.txt
