Metadata-Version: 2.0
Name: finix-wac
Version: 0.31
Summary: Writing RESTful API clients.
Home-page: https://github.com/finix-payments/wac
Author: Finix
Author-email: dev@finixpayments.com
License: Copyright (c) 2014 Balanced.
Requires-Dist: certifi (==0.0.8)
Requires-Dist: chardet (>=1.0)
Requires-Dist: simplejson (>=2.1)
Requires-Dist: iso8601
Requires-Dist: requests (>=1.2.3)
